bsedebtmarket/__init__.py
bsedebtmarket/parser.py
bsedebtmarket-0.1.0.dist-info/METADATA
bsedebtmarket-0.1.0.dist-info/WHEEL
bsedebtmarket-0.1.0.dist-info/entry_points.txt
bsedebtmarket-0.1.0.dist-info/top_level.txt
bsedebtmarket-0.1.0.dist-info/RECORD
