Metadata-Version: 2.1
Name: bsedebtmarket
Version: 0.1.0
Summary: A library to scrape BSE Debt Market and convert them to JSON.
Home-page: UNKNOWN
Author: Sagar Chand Agarwla
Author-email: sagar.agarwal@beyondirr.tech
License: UNKNOWN
Platform: UNKNOWN
Requires-Dist: beautifulsoup4
